llama_index/llms/sglang/__init__.py
llama_index/llms/sglang/base.py
llama_index/llms/sglang/utils.py
llama_index_llms_sglang-0.1.0.dist-info/METADATA
llama_index_llms_sglang-0.1.0.dist-info/WHEEL
llama_index_llms_sglang-0.1.0.dist-info/RECORD
