Metadata-Version: 2.4
Name: llama-index-llms-sglang
Version: 0.1.0
Summary: llama-index llms sglang integration
Author-email: Advik Sharma <scince5678@gmail.com>
License-Expression: MIT
Requires-Python: <4.0,>=3.9
Requires-Dist: llama-index-core<0.15,>=0.13.0
Requires-Dist: requests>=2.31.0
